performance_tool/__init__.py
performance_tool/evaluate_segmentation.py
performance_tool/manually_segmentation.py
performance_tool/performance_polygons.py
segmentation_evaluation-1.0.4.data/scripts/segmentation-evaluation
segmentation_evaluation-1.0.4.dist-info/LICENSE
segmentation_evaluation-1.0.4.dist-info/METADATA
segmentation_evaluation-1.0.4.dist-info/WHEEL
segmentation_evaluation-1.0.4.dist-info/top_level.txt
segmentation_evaluation-1.0.4.dist-info/RECORD
