Metadata-Version: 2.1
Name: segmentation-evaluation
Version: 1.0.4
Summary: Segmentation evaluation tool
Home-page: https://github.com/mett96/segmentation-evaluation
Author: Mattia Sanchioni, Alessandro Concetti
Author-email: mattia.sanchioni.dev@gmail.com, ale.concetti@gmail.com
License: GPLv3
Keywords: segmentation-evaluation segmentation evaluation image analysis image-analysis ground-truth
Platform: UNKNOWN
Classifier: Development Status :: 4 - Beta
Classifier: Intended Audience :: Developers
Classifier: Intended Audience :: Science/Research
Classifier: Programming Language :: Python :: 3
Classifier: Programming Language :: Python :: 3.6
Classifier: Programming Language :: Python :: 3.7
Classifier: License :: OSI Approved :: GNU General Public License v3 (GPLv3)
Classifier: Operating System :: OS Independent
Classifier: Natural Language :: English
Classifier: Programming Language :: Python :: Implementation :: PyPy
Classifier: Topic :: Scientific/Engineering :: Image Recognition
Requires-Python: >=3.6
Requires-Dist: numpy
Requires-Dist: Shapely
Requires-Dist: opencv-contrib-python (==3.4.2.17)
